{
  "timestamp": "2025-11-29T18:02:13.919342",
  "fundamentals": {
    "PE_Ratio": 37.32932,
    "Forward_PE": 33.555954,
    "PEG_Ratio": null,
    "Price_to_Book": 55.870567,
    "Price_to_Sales": 9.9438505,
    "EV_to_Revenue": 10.04,
    "EV_to_EBITDA": 28.864,
    "Profit_Margin": 0.26915002,
    "Operating_Margin": 0.31647,
    "Gross_Margin": 0.46905,
    "ROE": 1.7142199,
    "ROA": 0.22964,
    "Current_Ratio": 0.893,
    "Quick_Ratio": 0.771,
    "Debt_to_Equity": 152.411,
    "Revenue_Growth": 0.079,
    "Earnings_Growth": 0.912,
    "EPS": 7.47,
    "Book_Value_Per_Share": 4.991,
    "Dividend_Yield": 0.37,
    "Payout_Ratio": 0.1367,
    "Market_Cap": 4138242670592,
    "Enterprise_Value": 4178066014208,
    "Total_Debt": 112377004032,
    "Free_Cashflow": 78862254080,
    "Sector": "Technology",
    "Industry": "Consumer Electronics",
    "Company_Name": "Apple Inc."
  }
}